psggadgets/LICENSE.txt
psggadgets/README.md
psggadgets/__init__.py
psggadgets/__main__.py
psggadgets/gadget1.jpg
psggadgets/gadget2.jpg
psggadgets/gadget_CPU_Dashboard.py
psggadgets/gadget_CPU_Square.py
psggadgets/gadget_CPU_Top_Processes.py
psggadgets/gadget_Drive_Usage.py
psggadgets/gadget_RAM_Square.py
psggadgets/gadget_Time_Handwritten.py
psggadgets/gadget_Weather.py
psggadgets/gadget_psutil_Dashboard.py
psggadgets/gadgets.gif
psggadgets/psggadgets.ico
psggadgets/psggadgets.png
psggadgets/psggadgets.py
psggadgets-5.0.0.dist-info/LICENSE.txt
psggadgets-5.0.0.dist-info/METADATA
psggadgets-5.0.0.dist-info/WHEEL
psggadgets-5.0.0.dist-info/entry_points.txt
psggadgets-5.0.0.dist-info/top_level.txt
psggadgets-5.0.0.dist-info/RECORD
